nx584/__init__.py
nx584/api.py
nx584/client.py
nx584/controller.py
nx584/event_queue.py
nx584/mail.py
nx584/main.py
nx584/model.py
pynx584-0.8.2.data/scripts/nx584_client
pynx584-0.8.2.data/scripts/nx584_server
pynx584-0.8.2.dist-info/LICENSE
pynx584-0.8.2.dist-info/METADATA
pynx584-0.8.2.dist-info/WHEEL
pynx584-0.8.2.dist-info/pbr.json
pynx584-0.8.2.dist-info/top_level.txt
pynx584-0.8.2.dist-info/RECORD
